fab_controller
