Metadata-Version: 1.0
Name: fab-controller
Version: 0.9.12
Summary: Control an FAB finger pressure stimulator device.
Home-page: http://pypi.python.org/pypi/fab-controller/
Author: Ben Whalley
Author-email: benwhalley@gmail.com
License: LICENSE.txt
Platform: UNKNOWN
